docs/conf.py
scSHARP/__init__.py
scSHARP/check_tool_accuracy.py
scSHARP/gcn_model.py
scSHARP/grid_search.py
scSHARP/grid_search_generator.py
scSHARP/interpret.py
scSHARP/knn_search.py
scSHARP/pca_model.py
scSHARP/rdriver.r
scSHARP/sc_sharp.py
scSHARP/test_config.py
scSHARP/utilities.py
scSHARP/configs/2_15.txt
scSHARP/configs/2_25.txt
scSHARP/configs/2_40.txt
scSHARP/configs/2_60.txt
scSHARP/configs/3_15.txt
scSHARP/configs/3_25.txt
scSHARP/configs/3_40.txt
scSHARP/configs/3_60.txt
scSHARP/configs/4_15.txt
scSHARP/configs/4_25.txt
scSHARP/configs/4_40.txt
scSHARP/configs/4_60.txt
test/test_config.py
test/test_model.py
test/utilties_test.py
scSHARP-1.0.2.dist-info/LICENSE.txt
scSHARP-1.0.2.dist-info/METADATA
scSHARP-1.0.2.dist-info/WHEEL
scSHARP-1.0.2.dist-info/top_level.txt
scSHARP-1.0.2.dist-info/RECORD
