Metadata-Version: 2.1
Name: scSHARP
Version: 1.0.2
Summary: scSHARP tool for single cell consensus classification
Home-page: https://github.com/mperozek11/scSHARP_tool
Requires-Python: >=3.8.0
License-File: LICENSE.txt
Requires-Dist: pandas>=1.3.4
Requires-Dist: scikit-learn>=1.0.1
Requires-Dist: torch>=1.10.0
Requires-Dist: torch-geometric>=2.0.2
Requires-Dist: anndata>=0.8.0
Requires-Dist: scanpy>=1.9.1
Requires-Dist: rpy2>=3.5.3
Requires-Dist: captum>=0.5.0
